deepytorch/__init__.py
deepytorch-0.0.0.dist-info/METADATA
deepytorch-0.0.0.dist-info/WHEEL
deepytorch-0.0.0.dist-info/top_level.txt
deepytorch-0.0.0.dist-info/RECORD
