Metadata-Version: 2.1
Name: deepytorch
Version: 0.0.0
Summary: deepytorch
Home-page: https://www.aliyun.com
